{
  "airdrops": [],
  "alpha_checkins": [
    {
      "key": "today",
      "count": 90383
    },
    {
      "key": "yesterday",
      "count": 109146
    },
    {
      "key": "before_yesterday",
      "count": 108011
    }
  ],
  "last_rollover_date": "2026-03-21",
  "top3_tokens": [
    {
      "symbol": "GUA",
      "buyQuoteVolume": "965912576.78798",
      "trades": 4663032,
      "avgBuyAmount": "207.14"
    },
    {
      "symbol": "BSB",
      "buyQuoteVolume": "190612805.71575",
      "trades": 3245531,
      "avgBuyAmount": "58.73"
    },
    {
      "symbol": "UP",
      "buyQuoteVolume": "7694484.0789226",
      "trades": 438866,
      "avgBuyAmount": "17.53"
    }
  ],
  "bnb_price_usd": 644.73,
  "bnb_price_ts": 1774104323,
  "bnb_price_source": "coingecko"
}