{
  "airdrops": [],
  "alpha_checkins": [
    {
      "key": "today",
      "count": 96403
    },
    {
      "key": "yesterday",
      "count": 106369
    },
    {
      "key": "before_yesterday",
      "count": 105851
    }
  ],
  "last_rollover_date": "2026-03-18",
  "top3_tokens": [
    {
      "symbol": "GUA",
      "buyQuoteVolume": "1051673801.7552",
      "trades": 4092377,
      "avgBuyAmount": "256.98"
    },
    {
      "symbol": "VELVET",
      "buyQuoteVolume": "166353720.78443",
      "trades": 1725018,
      "avgBuyAmount": "96.44"
    },
    {
      "symbol": "BSB",
      "buyQuoteVolume": "15857171.15178",
      "trades": 659896,
      "avgBuyAmount": "24.03"
    }
  ],
  "bnb_price_usd": 649.34,
  "bnb_price_ts": 1773852323,
  "bnb_price_source": "coingecko"
}