{
  "airdrops": [],
  "alpha_checkins": [
    {
      "key": "today",
      "count": 111159
    },
    {
      "key": "yesterday",
      "count": 115648
    },
    {
      "key": "before_yesterday",
      "count": 114619
    }
  ],
  "last_rollover_date": "2026-03-23",
  "top3_tokens": [
    {
      "symbol": "GUA",
      "buyQuoteVolume": "1111633326.2456",
      "trades": 6289370,
      "avgBuyAmount": "176.75"
    },
    {
      "symbol": "BSB",
      "buyQuoteVolume": "270217247.66588",
      "trades": 4603476,
      "avgBuyAmount": "58.7"
    },
    {
      "symbol": "UP",
      "buyQuoteVolume": "52412208.396707",
      "trades": 2475764,
      "avgBuyAmount": "21.17"
    }
  ],
  "bnb_price_usd": 636.75,
  "bnb_price_ts": 1774308023,
  "bnb_price_source": "coingecko"
}