{
  "airdrops": [],
  "alpha_checkins": [
    {
      "key": "today",
      "count": 3310
    },
    {
      "key": "yesterday",
      "count": 106369
    },
    {
      "key": "before_yesterday",
      "count": 105851
    }
  ],
  "last_rollover_date": "2026-03-18",
  "top3_tokens": [
    {
      "symbol": "GUA",
      "buyQuoteVolume": "38645586.281756",
      "trades": 195442,
      "avgBuyAmount": "197.73"
    },
    {
      "symbol": "VELVET",
      "buyQuoteVolume": "2932939.5878796",
      "trades": 59022,
      "avgBuyAmount": "49.69"
    },
    {
      "symbol": "BSB",
      "buyQuoteVolume": "664223.37028192",
      "trades": 32808,
      "avgBuyAmount": "20.25"
    }
  ],
  "bnb_price_usd": 668.38,
  "bnb_price_ts": 1773795624,
  "bnb_price_source": "coingecko"
}